setup.py
anmolpant/Binomialdistribution.py
anmolpant/Gaussiandistribution.py
anmolpant/Generaldistribution.py
anmolpant/__init__.py
anmolpant.egg-info/PKG-INFO
anmolpant.egg-info/SOURCES.txt
anmolpant.egg-info/dependency_links.txt
anmolpant.egg-info/not-zip-safe
anmolpant.egg-info/top_level.txt